mmdl/__init__.py
mmdl/ask.py
mmdl/cli.py
mmdl/globals.py
mmdl/mdl.py
mmdl/utils.py
mmdl/yt_utils.py
mmdl-0.1.6.dist-info/LICENSE
mmdl-0.1.6.dist-info/METADATA
mmdl-0.1.6.dist-info/WHEEL
mmdl-0.1.6.dist-info/entry_points.txt
mmdl-0.1.6.dist-info/top_level.txt
mmdl-0.1.6.dist-info/RECORD
